braidgenerator/__init__.py
braidgenerator/braidword.py
braidgenerator/markovchain.py
braidgenerator/decorators/__init__.py
braidgenerator/decorators/braidword.py
braidgenerator/decorators/markovchain.py
braidgenerator-1.0.1.dist-info/LICENSE.md
braidgenerator-1.0.1.dist-info/METADATA
braidgenerator-1.0.1.dist-info/WHEEL
braidgenerator-1.0.1.dist-info/top_level.txt
braidgenerator-1.0.1.dist-info/RECORD
