Metadata-Version: 2.1
Name: braidgenerator
Version: 1.0.1
Summary: Braid Generator
Home-page: https://github.com/Algebra8/Knots
Author: Braid Generator Team
Author-email: mmnasrollahi@ucdavis.edu
License: MIT
Platform: UNKNOWN
Classifier: License :: OSI Approved :: MIT License
Classifier: Programming Language :: Python :: 3
Classifier: Programming Language :: Python :: 3.6
Classifier: Programming Language :: Python :: 3.7
Classifier: Topic :: Software Development :: Libraries
Classifier: Topic :: Software Development :: Libraries :: Python Modules
Classifier: Intended Audience :: Developers
Classifier: Intended Audience :: Education
Classifier: Intended Audience :: Science/Research
Requires-Dist: pandas
Provides-Extra: tests
Requires-Dist: unittest ; extra == 'tests'
